interframe/__init__.py
interframe/interframe.py
interframe-0.0.3.dist-info/LICENSE
interframe-0.0.3.dist-info/METADATA
interframe-0.0.3.dist-info/WHEEL
interframe-0.0.3.dist-info/entry_points.txt
interframe-0.0.3.dist-info/top_level.txt
interframe-0.0.3.dist-info/RECORD
