Metadata-Version: 2.1
Name: interframe
Version: 0.0.3
Summary: Python CLI for generating intermediate image frames by interpolating between input key frames.
Home-page: https://github.com/coryg89/interframe
Author: Cory Gross
Author-email: coryg89@gmail.com
Project-URL: Bug Tracker, https://github.com/coryg89/interframe/issues
Classifier: Programming Language :: Python :: 3
Classifier: License :: OSI Approved :: MIT License
Classifier: Operating System :: OS Independent
Requires-Python: >=3.6
License-File: LICENSE
Requires-Dist: numpy
Requires-Dist: mediapy
Requires-Dist: tensorflow
Requires-Dist: tensorflow-hub
